pytest_localftpserver/__init__.py
pytest_localftpserver/_version.py
pytest_localftpserver/default_keycert.pem
pytest_localftpserver/helper_functions.py
pytest_localftpserver/plugin.py
pytest_localftpserver/servers.py
pytest_localftpserver-1.5.0.dist-info/licenses/AUTHORS.rst
pytest_localftpserver-1.5.0.dist-info/licenses/LICENSE
pytest_localftpserver-1.5.0.dist-info/METADATA
pytest_localftpserver-1.5.0.dist-info/WHEEL
pytest_localftpserver-1.5.0.dist-info/entry_points.txt
pytest_localftpserver-1.5.0.dist-info/top_level.txt
pytest_localftpserver-1.5.0.dist-info/RECORD
