Metadata-Version: 2.4
Name: pytest_localftpserver
Version: 1.5.0
Summary: A PyTest plugin which provides an FTP fixture for your tests
Author-email: Oz N Tiram <oz.tiram@gmail.com>
Project-URL: homepage, https://github.com/oz123/pytest-localftpserver
Classifier: Development Status :: 5 - Production/Stable
Classifier: Intended Audience :: Developers
Classifier: Operating System :: MacOS :: MacOS X
Classifier: Operating System :: Microsoft :: Windows
Classifier: Operating System :: POSIX :: Linux
Classifier: Operating System :: POSIX
Classifier: License :: OSI Approved :: MIT License
Classifier: Natural Language :: English
Classifier: Programming Language :: Python :: 3
Classifier: Programming Language :: Python :: 3.10
Classifier: Programming Language :: Python :: 3.11
Classifier: Programming Language :: Python :: 3.12
Classifier: Programming Language :: Python :: 3.13
Classifier: Programming Language :: Python :: 3 :: Only
Classifier: Framework :: Pytest
Classifier: Topic :: Software Development :: Testing
Classifier: Topic :: Software Development :: Testing :: Mocking
License-File: LICENSE
License-File: AUTHORS.rst
Requires-Dist: pyftpdlib>=1.2.0
Requires-Dist: PyOpenSSL
Requires-Dist: pytest
Requires-Dist: cryptography>=43
Dynamic: license-file
